LICENSE.txt
README.md
pyproject.toml
setup.cfg
setup.py
readmet/__init__.py
readmet/_version.py
readmet/akterm.py
readmet/dmna.py
readmet/scintec1.py
readmet/toa5.py
readmet.egg-info/PKG-INFO
readmet.egg-info/SOURCES.txt
readmet.egg-info/dependency_links.txt
readmet.egg-info/requires.txt
readmet.egg-info/top_level.txt