Metadata-Version: 2.4
Name: readmet
Version: 0.8.42
Summary: Python library for reading and writing less popular formats used in meteorology.
Home-page: 
Author: Clemens Drüe
Author-email: druee@uni-trier.de
License: EUPL-1.2
License-File: LICENSE.txt
Requires-Dist: numpy
Requires-Dist: pandas
Dynamic: author
Dynamic: author-email
Dynamic: description
Dynamic: description-content-type
Dynamic: license
Dynamic: license-file
Dynamic: requires-dist
Dynamic: summary
